nazo_image_utils/__init__.py
nazo_image_utils/process_image.py
nazo_image_utils/rand_image.cp38-win_amd64.pyd
nazo_image_utils/rand_image.cpp
nazo_image_utils/rand_image.pyi
nazo_image_utils/rand_image.pyx
nazo_image_utils-0.0.5.dist-info/LICENSE
nazo_image_utils-0.0.5.dist-info/METADATA
nazo_image_utils-0.0.5.dist-info/WHEEL
nazo_image_utils-0.0.5.dist-info/top_level.txt
nazo_image_utils-0.0.5.dist-info/RECORD
