Metadata-Version: 2.1
Name: nazo_image_utils
Version: 0.0.5
Summary: A tool for generating random images
Author-email: bymoye <s3moye@gmail.com>
License: MIT License
Project-URL: Homepage, https://github.com/bymoye/nazo_image_utils
Project-URL: Bug Tracker, https://github.com/bymoye/nazo_image_utils/issues
Classifier: Development Status :: 5 - Production/Stable
Classifier: Programming Language :: Python :: 3.8
Classifier: Programming Language :: Python :: 3.9
Classifier: Programming Language :: Python :: 3.10
Classifier: Programming Language :: Python :: 3.11
Classifier: Programming Language :: Python :: 3.12
Classifier: Programming Language :: Python :: 3.13
Classifier: Programming Language :: Cython
Classifier: Operating System :: POSIX :: Linux
Classifier: Operating System :: MacOS :: MacOS X
Classifier: Operating System :: Microsoft :: Windows
Classifier: Topic :: Software Development :: Libraries :: Python Modules
Requires-Python: >=3.8
License-File: LICENSE
Requires-Dist: Pillow
Requires-Dist: ujson
Requires-Dist: tqdm
Requires-Dist: webp-support
Requires-Dist: nazo-rand
